Workbook

Sheet Dataset 1
A1: gender | B1: age | C1: Investment_Avenues | D1: Mutual_Funds | E1: Equity_Market | F1: Debentures | G1: Government_Bonds | H1: Fixed_Deposits | I1: PPF | J1: Gold | K1: Stock_Marktet | L1: Factor | M1: Objective | N1: Purpose | O1: Duration | P1: Invest_Monitor | Q1: Expect | R1: Avenue | S1: What are your savings objectives? | T1: Reason_Equity | U1: Reason_Mutual | V1: Reason_Bonds | W1: Reason_FD | X1: Source | Z1: gender | AA1: Duration | AB1: Expect
A2: Female | B2: 34 | C2: Yes | D2: 1 | E2: 2 | F2: 5 | G2: 3 | H2: 7 | I2: 6 | J2: 4 | K2: Yes | L2: Returns | M2: Capital Appreciation | N2: Wealth Creation | O2: 1-3 years | P2: Monthly | Q2: 20%-30% | R2: Mutual Fund | S2: Retirement Plan | T2: Capital Appreciation | U2: Better Returns | V2: Safe Investment | W2: Fixed Returns | X2: Newspapers and Magazines | Z2: Female | AA2: 1-3 years | AB2: 20%-30%
A3: Female | B3: 23 | C3: Yes | D3: 4 | E3: 3 | F3: 2 | G3: 1 | H3: 5 | I3: 6 | J3: 7 | K3: No | L3: Locking Period | M3: Capital Appreciation | N3: Wealth Creation | O3: More than 5 years | P3: Weekly | Q3: 20%-30% | R3: Mutual Fund | S3: Health Care | T3: Dividend | U3: Better Returns | V3: Safe Investment | W3: High Interest Rates | X3: Financial Consultants | Z3: Female | AA3: More than 5 years | AB3: 20%-30%
A4: Male | B4: 30 | C4: Yes | D4: 3 | E4: 6 | F4: 4 | G4: 2 | H4: 5 | I4: 1 | J4: 7 | K4: Yes | L4: Returns | M4: Capital Appreciation | N4: Wealth Creation | O4: 3-5 years | P4: Daily | Q4: 20%-30% | R4: Equity | S4: Retirement Plan | T4: Capital Appreciation | U4: Tax Benefits | V4: Assured Returns | W4: Fixed Returns | X4: Television | Z4: Male | AA4: 3-5 years | AB4: 20%-30%
A5: Male | B5: 22 | D5: 2 | E5: 1 | F5: 3 | G5: 7 | H5: 6 | I5: 4 | J5: 5 | K5: Yes | L5: Returns | M5: Income | N5: Wealth Creation | O5: Less than 1 year | P5: Daily | Q5: 10%-20% | R5: Equity | S5: Retirement Plan | T5: Dividend | U5: Fund Diversification | V5: Tax Incentives | W5: High Interest Rates | X5: Internet | Z5: Male | AA5: Less than 1 year | AB5: 10%-20%
A6: Female | B6: 24 | C6: No | D6: 2 | E6: 1 | F6: 3 | G6: 6 | H6: 4 | I6: 5 | J6: 7 | K6: No | L6: Returns | M6: Income | N6: Wealth Creation | O6: Less than 1 year | P6: Daily | Q6: 20%-30% | R6: Equity | S6: Retirement Plan | T6: Capital Appreciation | U6: Better Returns | V6: Safe Investment | W6: Risk Free | X6: Internet | Z6: Female | AA6: Less than 1 year | AB6: 20%-30%
A7: Female | B7: 24 | C7: No | D7: 7 | E7: 5 | F7: 4 | G7: 6 | H7: 3 | I7: 1 | J7: 2 | K7: No | L7: Risk | M7: Capital Appreciation | N7: Wealth Creation | O7: 1-3 years | P7: Daily | Q7: 30%-40% | R7: Mutual Fund | S7: Retirement Plan | T7: Liquidity | U7: Fund Diversification | V7: Safe Investment | W7: Risk Free | X7: Internet | Z7: Female | AA7: 1-3 years | AB7: 30%-40%
A8: Female | B8: 27 | C8: Yes | D8: 3 | E8: 6 | F8: 4 | G8: 2 | H8: 5 | I8: 1 | J8: 7 | K8: Yes | L8: Returns | M8: Capital Appreciation | N8: Wealth Creation | O8: 3-5 years | P8: Monthly | Q8: 20%-30% | R8: Equity | S8: Retirement Plan | T8: Capital Appreciation | U8: Better Returns | V8: Assured Returns | W8: High Interest Rates | X8: Financial Consultants | Z8: Female | AA8: 3-5 years | AB8: 20%-30%
A9: Male | B9: 21 | C9: Yes | D9: 2 | E9: 3 | F9: 7 | G9: 4 | H9: 6 | I9: 1 | J9: 5 | K9: Yes | L9: Risk | M9: Capital Appreciation | N9: Wealth Creation | O9: 3-5 years | P9: Monthly | Q9: 20%-30% | R9: Mutual Fund | S9: Retirement Plan | T9: Capital Appreciation | U9: Better Returns | V9: Assured Returns | W9: Risk Free | X9: Newspapers and Magazines | Z9: Male | AA9: 3-5 years | AB9: 20%-30%
A10: Male | B10: 35 | C10: Yes | D10: 2 | E10: 4 | F10: 7 | G10: 5 | H10: 3 | I10: 1 | J10: 6 | K10: Yes | L10: Returns | M10: Growth | N10: Savings for Future | O10: 1-3 years | P10: Weekly | Q10: 20%-30% | R10: Equity | S10: Retirement Plan | T10: Capital Appreciation | U10: Fund Diversification | V10: Safe Investment | W10: Fixed Returns | X10: Television | Z10: Male | AA10: 1-3 years | AB10: 20%-30%
A11: Male | B11: 31 | C11: Yes | D11: 1 | E11: 3 | F11: 7 | G11: 4 | H11: 5 | I11: 2 | J11: 6 | K11: Yes | L11: Returns | M11: Capital Appreciation | N11: Wealth Creation | O11: 3-5 years | P11: Monthly | Q11: 30%-40% | R11: Fixed Deposits | S11: Retirement Plan | T11: Capital Appreciation | U11: Fund Diversification | V11: Assured Returns | W11: Fixed Returns | X11: Newspapers and Magazines | Z11: Male | AA11: 3-5 years | AB11: 30%-40%
A12: Female | B12: 35 | C12: Yes | D12: 2 | E12: 4 | F12: 7 | G12: 5 | H12: 3 | I12: 1 | J12: 6 | K12: Yes | L12: Risk | M12: Growth | N12: Savings for Future | O12: 3-5 years | P12: Monthly | Q12: 20%-30% | R12: Mutual Fund | S12: Retirement Plan | T12: Capital Appreciation | U12: Better Returns | V12: Assured Returns | W12: Risk Free | X12: Financial Consultants | Z12: Female | AA12: 3-5 years | AB12: 20%-30%
A13: Male | B13: 29 | C13: Yes | D13: 2 | E13: 5 | F13: 7 | G13: 6 | H13: 3 | I13: 1 | J13: 4 | K13: Yes | L13: Risk | M13: Capital Appreciation | N13: Wealth Creation | O13: 1-3 years | P13: Monthly | Q13: 20%-30% | R13: Mutual Fund | S13: Retirement Plan | T13: Capital Appreciation | U13: Fund Diversification | V13: Assured Returns | W13: Fixed Returns | X13: Financial Consultants | Z13: Male | AA13: 1-3 years | AB13: 20%-30%
A14: Female | B14: 21 | C14: No | D14: 1 | E14: 2 | F14: 3 | G14: 4 | H14: 5 | I14: 6 | J14: 7 | K14: No | L14: Returns | M14: Capital Appreciation | N14: Savings for Future | O14: 1-3 years | P14: Weekly | Q14: 20%-30% | R14: Mutual Fund | S14: Education | T14: Dividend | U14: Better Returns | V14: Safe Investment | W14: Risk Free | X14: Internet | Z14: Female | AA14: 1-3 years | AB14: 20%-30%
A15: Female | B15: 28 | C15: Yes | D15: 2 | E15: 3 | F15: 7 | G15: 4 | H15: 5 | I15: 1 | J15: 6 | K15: Yes | L15: Returns | M15: Capital Appreciation | N15: Wealth Creation | O15: 1-3 years | P15: Monthly | Q15: 20%-30% | R15: Mutual Fund | S15: Retirement Plan | T15: Capital Appreciation | U15: Fund Diversification | V15: Assured Returns | W15: Risk Free | X15: Newspapers and Magazines | Z15: Female | AA15: 1-3 years | AB15: 20%-30%
A16: Female | B16: 25 | C16: Yes | D16: 2 | E16: 3 | F16: 7 | G16: 5 | H16: 4 | I16: 1 | J16: 6 | K16: Yes | L16: Returns | M16: Capital Appreciation | N16: Wealth Creation | O16: 1-3 years | P16: Monthly | Q16: 20%-30% | R16: Fixed Deposits | S16: Health Care | T16: Dividend | U16: Better Returns | V16: Assured Returns | W16: Risk Free | X16: Financial Consultants | Z16: Female | AA16: 1-3 years | AB16: 20%-30%
A17: Male | B17: 27 | C17: Yes | D17: 2 | E17: 3 | F17: 7 | G17: 5 | H17: 4 | I17: 1 | J17: 6 | K17: Yes | L17: Returns | M17: Capital Appreciation | N17: Wealth Creation | O17: 1-3 years | P17: Monthly | Q17: 20%-30% | R17: Mutual Fund | S17: Health Care | T17: Capital Appreciation | U17: Fund Diversification | V17: Assured Returns | W17: Risk Free | X17: Newspapers and Magazines | Z17: Male | AA17: 1-3 years | AB17: 20%-30%
... A41: Male | B41: 29 | C41: Yes | D41: 4 | E41: 3 | F41: 5 | G41: 7 | H41: 2 | I41: 1 | J41: 6 | K41: Yes | L41: Returns | M41: Capital Appreciation | N41: Wealth Creation | O41: 3-5 years | P41: Monthly | Q41: 20%-30% | R41: Fixed Deposits | S41: Retirement Plan | T41: Dividend | U41: Better Returns | V41: Safe Investment | W41: Fixed Returns | X41: Financial Consultants | Z41: Male | AA41: 3-5 years | AB41: 20%-30%

Sheet Scatter Chart
A1: Gender | B1: Duration | C1: Expect
A2: =IF('Dataset 1'!Z2="Male",1,0) -> 0 | B2: =IF('Dataset 1'!AA2="Less than 1 year",0.5, IF('Dataset 1'!AA2="1-3 years",2, IF('Dataset 1'!AA2="3-5 years",4, IF('Dataset 1'!AA2="More than 5 years",6,"")))) -> 2 | C2: =IF('Dataset 1'!AB2="10%-20%",15, IF('Dataset 1'!AB2="20%-30%",25, IF('Dataset 1'!AB2="30%-40%",35, IF('Dataset 1'!AB2="40%-50%",45, IF('Dataset 1'!AB2="Less than 10%",5,""))))) -> 25 | F2: Gender | G2: Duration | H2: Expect
A3: =IF('Dataset 1'!Z3="Male",1,0) -> 0 | B3: =IF('Dataset 1'!AA3="Less than 1 year",0.5, IF('Dataset 1'!AA3="1-3 years",2, IF('Dataset 1'!AA3="3-5 years",4, IF('Dataset 1'!AA3="More than 5 years",6,"")))) -> 6 | C3: =IF('Dataset 1'!AB3="10%-20%",15, IF('Dataset 1'!AB3="20%-30%",25, IF('Dataset 1'!AB3="30%-40%",35, IF('Dataset 1'!AB3="40%-50%",45, IF('Dataset 1'!AB3="Less than 10%",5,""))))) -> 25 | E3: Gender | F3: 1
A4: =IF('Dataset 1'!Z4="Male",1,0) -> 1 | B4: =IF('Dataset 1'!AA4="Less than 1 year",0.5, IF('Dataset 1'!AA4="1-3 years",2, IF('Dataset 1'!AA4="3-5 years",4, IF('Dataset 1'!AA4="More than 5 years",6,"")))) -> 4 | C4: =IF('Dataset 1'!AB4="10%-20%",15, IF('Dataset 1'!AB4="20%-30%",25, IF('Dataset 1'!AB4="30%-40%",35, IF('Dataset 1'!AB4="40%-50%",45, IF('Dataset 1'!AB4="Less than 10%",5,""))))) -> 25 | E4: Duration | F4: -0.08008119 | G4: 1
A5: =IF('Dataset 1'!Z5="Male",1,0) -> 1 | B5: =IF('Dataset 1'!AA5="Less than 1 year",0.5, IF('Dataset 1'!AA5="1-3 years",2, IF('Dataset 1'!AA5="3-5 years",4, IF('Dataset 1'!AA5="More than 5 years",6,"")))) -> 0.5 | C5: =IF('Dataset 1'!AB5="10%-20%",15, IF('Dataset 1'!AB5="20%-30%",25, IF('Dataset 1'!AB5="30%-40%",35, IF('Dataset 1'!AB5="40%-50%",45, IF('Dataset 1'!AB5="Less than 10%",5,""))))) -> 15 | E5: Expect | F5: -0.029049645 | G5: 0.25822264 | H5: 1
A6: =IF('Dataset 1'!Z6="Male",1,0) -> 0 | B6: =IF('Dataset 1'!AA6="Less than 1 year",0.5, IF('Dataset 1'!AA6="1-3 years",2, IF('Dataset 1'!AA6="3-5 years",4, IF('Dataset 1'!AA6="More than 5 years",6,"")))) -> 0.5 | C6: =IF('Dataset 1'!AB6="10%-20%",15, IF('Dataset 1'!AB6="20%-30%",25, IF('Dataset 1'!AB6="30%-40%",35, IF('Dataset 1'!AB6="40%-50%",45, IF('Dataset 1'!AB6="Less than 10%",5,""))))) -> 25
A7: =IF('Dataset 1'!Z7="Male",1,0) -> 0 | B7: =IF('Dataset 1'!AA7="Less than 1 year",0.5, IF('Dataset 1'!AA7="1-3 years",2, IF('Dataset 1'!AA7="3-5 years",4, IF('Dataset 1'!AA7="More than 5 years",6,"")))) -> 2 | C7: =IF('Dataset 1'!AB7="10%-20%",15, IF('Dataset 1'!AB7="20%-30%",25, IF('Dataset 1'!AB7="30%-40%",35, IF('Dataset 1'!AB7="40%-50%",45, IF('Dataset 1'!AB7="Less than 10%",5,""))))) -> 35
A8: =IF('Dataset 1'!Z8="Male",1,0) -> 0 | B8: =IF('Dataset 1'!AA8="Less than 1 year",0.5, IF('Dataset 1'!AA8="1-3 years",2, IF('Dataset 1'!AA8="3-5 years",4, IF('Dataset 1'!AA8="More than 5 years",6,"")))) -> 4 | C8: =IF('Dataset 1'!AB8="10%-20%",15, IF('Dataset 1'!AB8="20%-30%",25, IF('Dataset 1'!AB8="30%-40%",35, IF('Dataset 1'!AB8="40%-50%",45, IF('Dataset 1'!AB8="Less than 10%",5,""))))) -> 25
A9: =IF('Dataset 1'!Z9="Male",1,0) -> 1 | B9: =IF('Dataset 1'!AA9="Less than 1 year",0.5, IF('Dataset 1'!AA9="1-3 years",2, IF('Dataset 1'!AA9="3-5 years",4, IF('Dataset 1'!AA9="More than 5 years",6,"")))) -> 4 | C9: =IF('Dataset 1'!AB9="10%-20%",15, IF('Dataset 1'!AB9="20%-30%",25, IF('Dataset 1'!AB9="30%-40%",35, IF('Dataset 1'!AB9="40%-50%",45, IF('Dataset 1'!AB9="Less than 10%",5,""))))) -> 25
A10: =IF('Dataset 1'!Z10="Male",1,0) -> 1 | B10: =IF('Dataset 1'!AA10="Less than 1 year",0.5, IF('Dataset 1'!AA10="1-3 years",2, IF('Dataset 1'!AA10="3-5 years",4, IF('Dataset 1'!AA10="More than 5 years",6,"")))) -> 2 | C10: =IF('Dataset 1'!AB10="10%-20%",15, IF('Dataset 1'!AB10="20%-30%",25, IF('Dataset 1'!AB10="30%-40%",35, IF('Dataset 1'!AB10="40%-50%",45, IF('Dataset 1'!AB10="Less than 10%",5,""))))) -> 25
A11: =IF('Dataset 1'!Z11="Male",1,0) -> 1 | B11: =IF('Dataset 1'!AA11="Less than 1 year",0.5, IF('Dataset 1'!AA11="1-3 years",2, IF('Dataset 1'!AA11="3-5 years",4, IF('Dataset 1'!AA11="More than 5 years",6,"")))) -> 4 | C11: =IF('Dataset 1'!AB11="10%-20%",15, IF('Dataset 1'!AB11="20%-30%",25, IF('Dataset 1'!AB11="30%-40%",35, IF('Dataset 1'!AB11="40%-50%",45, IF('Dataset 1'!AB11="Less than 10%",5,""))))) -> 35
A12: =IF('Dataset 1'!Z12="Male",1,0) -> 0 | B12: =IF('Dataset 1'!AA12="Less than 1 year",0.5, IF('Dataset 1'!AA12="1-3 years",2, IF('Dataset 1'!AA12="3-5 years",4, IF('Dataset 1'!AA12="More than 5 years",6,"")))) -> 4 | C12: =IF('Dataset 1'!AB12="10%-20%",15, IF('Dataset 1'!AB12="20%-30%",25, IF('Dataset 1'!AB12="30%-40%",35, IF('Dataset 1'!AB12="40%-50%",45, IF('Dataset 1'!AB12="Less than 10%",5,""))))) -> 25
A13: =IF('Dataset 1'!Z13="Male",1,0) -> 1 | B13: =IF('Dataset 1'!AA13="Less than 1 year",0.5, IF('Dataset 1'!AA13="1-3 years",2, IF('Dataset 1'!AA13="3-5 years",4, IF('Dataset 1'!AA13="More than 5 years",6,"")))) -> 2 | C13: =IF('Dataset 1'!AB13="10%-20%",15, IF('Dataset 1'!AB13="20%-30%",25, IF('Dataset 1'!AB13="30%-40%",35, IF('Dataset 1'!AB13="40%-50%",45, IF('Dataset 1'!AB13="Less than 10%",5,""))))) -> 25
A14: =IF('Dataset 1'!Z14="Male",1,0) -> 0 | B14: =IF('Dataset 1'!AA14="Less than 1 year",0.5, IF('Dataset 1'!AA14="1-3 years",2, IF('Dataset 1'!AA14="3-5 years",4, IF('Dataset 1'!AA14="More than 5 years",6,"")))) -> 2 | C14: =IF('Dataset 1'!AB14="10%-20%",15, IF('Dataset 1'!AB14="20%-30%",25, IF('Dataset 1'!AB14="30%-40%",35, IF('Dataset 1'!AB14="40%-50%",45, IF('Dataset 1'!AB14="Less than 10%",5,""))))) -> 25
A15: =IF('Dataset 1'!Z15="Male",1,0) -> 0 | B15: =IF('Dataset 1'!AA15="Less than 1 year",0.5, IF('Dataset 1'!AA15="1-3 years",2, IF('Dataset 1'!AA15="3-5 years",4, IF('Dataset 1'!AA15="More than 5 years",6,"")))) -> 2 | C15: =IF('Dataset 1'!AB15="10%-20%",15, IF('Dataset 1'!AB15="20%-30%",25, IF('Dataset 1'!AB15="30%-40%",35, IF('Dataset 1'!AB15="40%-50%",45, IF('Dataset 1'!AB15="Less than 10%",5,""))))) -> 25
A16: =IF('Dataset 1'!Z16="Male",1,0) -> 0 | B16: =IF('Dataset 1'!AA16="Less than 1 year",0.5, IF('Dataset 1'!AA16="1-3 years",2, IF('Dataset 1'!AA16="3-5 years",4, IF('Dataset 1'!AA16="More than 5 years",6,"")))) -> 2 | C16: =IF('Dataset 1'!AB16="10%-20%",15, IF('Dataset 1'!AB16="20%-30%",25, IF('Dataset 1'!AB16="30%-40%",35, IF('Dataset 1'!AB16="40%-50%",45, IF('Dataset 1'!AB16="Less than 10%",5,""))))) -> 25
A17: =IF('Dataset 1'!Z17="Male",1,0) -> 1 | B17: =IF('Dataset 1'!AA17="Less than 1 year",0.5, IF('Dataset 1'!AA17="1-3 years",2, IF('Dataset 1'!AA17="3-5 years",4, IF('Dataset 1'!AA17="More than 5 years",6,"")))) -> 2 | C17: =IF('Dataset 1'!AB17="10%-20%",15, IF('Dataset 1'!AB17="20%-30%",25, IF('Dataset 1'!AB17="30%-40%",35, IF('Dataset 1'!AB17="40%-50%",45, IF('Dataset 1'!AB17="Less than 10%",5,""))))) -> 25
... A41: =IF('Dataset 1'!Z41="Male",1,0) -> 1 | B41: =IF('Dataset 1'!AA41="Less than 1 year",0.5, IF('Dataset 1'!AA41="1-3 years",2, IF('Dataset 1'!AA41="3-5 years",4, IF('Dataset 1'!AA41="More than 5 years",6,"")))) -> 4 | C41: =IF('Dataset 1'!AB41="10%-20%",15, IF('Dataset 1'!AB41="20%-30%",25, IF('Dataset 1'!AB41="30%-40%",35, IF('Dataset 1'!AB41="40%-50%",45, IF('Dataset 1'!AB41="Less than 10%",5,""))))) -> 25

Sheet Bubble Chart
A1: Gender | B1: Duration | C1: Expect
A2: 0 | B2: 2 | C2: 25
A3: 0 | B3: 6 | C3: 25
A4: 1 | B4: 4 | C4: 25
A5: 1 | B5: 0.5 | C5: 15
A6: 0 | B6: 0.5 | C6: 25
A7: 0 | B7: 2 | C7: 35
A8: 0 | B8: 4 | C8: 25
A9: 1 | B9: 4 | C9: 25
A10: 1 | B10: 2 | C10: 25
A11: 1 | B11: 4 | C11: 35
A12: 0 | B12: 4 | C12: 25
A13: 1 | B13: 2 | C13: 25
... A41: 1 | B41: 4 | C41: 25
